{"SubashLamaProfile": {"stars": 1, "forks": 0}, "softupakaranstagingecommerce": {"stars": 1, "forks": 0}, "Telemery-Metasploit-FrameworkFramework-stack": {"stars": 0, "forks": 0}, "ParrotOSv1": {"stars": 1, "forks": 0}, "Subash107": {"stars": 1, "forks": 0}, "cookie_defender_bowl": {"stars": 1, "forks": 0}, "Scripts": {"stars": 1, "forks": 0}, "pentest-helper": {"stars": 1, "forks": 0}, "wazuh-docker-stack-2": {"stars": 1, "forks": 0}, "nativus_erp_with_prometheus_grafana_v6": {"stars": 0, "forks": 0}}
